Metadata-Version: 2.1
Name: MetaMatching
Version: 1.0.1
Summary: An integrated deep learning framework for the interpretation of untargeted metabolomics data
Author: Leqi Tian
Author-email: leqitian@link.cuhk.edu.cn
Requires-Python: >=3.9
License-File: LICENSE.txt
